mbta/__init__.py
mbta/performance.py
mbta/response.py
mbta/utils.py
mbta-0.0.4.dist-info/LICENSE
mbta-0.0.4.dist-info/METADATA
mbta-0.0.4.dist-info/WHEEL
mbta-0.0.4.dist-info/top_level.txt
mbta-0.0.4.dist-info/RECORD
